{
  "generated_at": 1784040980,
  "source": "openweathermap 2.5",
  "destinations": {
    "abu-dhabi-hotels-best-views": {
      "temp_c": 33.21,
      "feels_like_c": 40.21,
      "condition_id": 803,
      "condition_main": "Clouds",
      "condition_description": "broken clouds",
      "clouds_pct": 78,
      "visibility_m": 10000,
      "sunrise": 1783993341,
      "sunset": 1784042035,
      "view_index": 75,
      "view_rating": "Excellent",
      "timezone": "Asia/Dubai",
      "coords": {
        "lat": 24.47779,
        "lng": 54.36981,
        "n_hotels": 12
      },
      "fetched_at": 1784040793
    },
    "algarve-hotels-best-views": {
      "temp_c": 26.12,
      "feels_like_c": 26.12,
      "condition_id": 800,
      "condition_main": "Clear",
      "condition_description": "clear sky",
      "clouds_pct": 2,
      "visibility_m": 10000,
      "sunrise": 1784006644,
      "sunset": 1784058814,
      "view_index": 100,
      "view_rating": "Perfect",
      "timezone": "Europe/Lisbon",
      "coords": {
        "lat": 37.10928,
        "lng": -8.2971,
        "n_hotels": 17
      },
      "fetched_at": 1784040795
    },
    "amalfi-coast-hotels-best-view": {
      "temp_c": 26.93,
      "feels_like_c": 28.28,
      "condition_id": 800,
      "condition_main": "Clear",
      "condition_description": "clear sky",
      "clouds_pct": 7,
      "visibility_m": 10000,
      "sunrise": 1784000558,
      "sunset": 1784053943,
      "view_index": 99,
      "view_rating": "Perfect",
      "timezone": "Europe/Rome",
      "coords": {
        "lat": 40.62869,
        "lng": 14.52835,
        "n_hotels": 18
      },
      "fetched_at": 1784040797
    },
    "amsterdam-hotels-best-views": {
      "temp_c": 28.39,
      "feels_like_c": 29.11,
      "condition_id": 800,
      "condition_main": "Clear",
      "condition_description": "clear sky",
      "clouds_pct": 0,
      "visibility_m": 10000,
      "sunrise": 1784000093,
      "sunset": 1784059032,
      "view_index": 100,
      "view_rating": "Perfect",
      "timezone": "Europe/Amsterdam",
      "coords": {
        "lat": 52.37071,
        "lng": 4.89566,
        "n_hotels": 18
      },
      "fetched_at": 1784040798
    },
    "antalya-hotels-view": {
      "temp_c": 30.88,
      "feels_like_c": 34.35,
      "condition_id": 800,
      "condition_main": "Clear",
      "condition_description": "clear sky",
      "clouds_pct": 0,
      "visibility_m": 10000,
      "sunrise": 1783997277,
      "sunset": 1784049375,
      "view_index": 100,
      "view_rating": "Perfect",
      "timezone": "Europe/Istanbul",
      "coords": {
        "lat": 36.86361,
        "lng": 30.87891,
        "n_hotels": 7
      },
      "fetched_at": 1784040800
    },
    "athens-best-hotels-view": {
      "temp_c": 32.09,
      "feels_like_c": 31.89,
      "condition_id": 800,
      "condition_main": "Clear",
      "condition_description": "clear sky",
      "clouds_pct": 0,
      "visibility_m": 10000,
      "sunrise": 1783998811,
      "sunset": 1784051272,
      "view_index": 100,
      "view_rating": "Perfect",
      "timezone": "Europe/Athens",
      "coords": {
        "lat": 37.97285,
        "lng": 23.73254,
        "n_hotels": 16
      },
      "fetched_at": 1784040802
    },
    "auckland-hotels-best-view": {
      "temp_c": 8.34,
      "feels_like_c": 8.34,
      "condition_id": 800,
      "condition_main": "Clear",
      "condition_description": "clear sky",
      "clouds_pct": 3,
      "visibility_m": 10000,
      "sunrise": 1784057463,
      "sunset": 1784092932,
      "view_index": 100,
      "view_rating": "Perfect",
      "timezone": "Pacific/Auckland",
      "coords": {
        "lat": -36.84727,
        "lng": 174.76349,
        "n_hotels": 17
      },
      "fetched_at": 1784040803
    },
    "bali-hotels-resorts-best-view": {
      "temp_c": 22.25,
      "feels_like_c": 22.88,
      "condition_id": 800,
      "condition_main": "Clear",
      "condition_description": "clear sky",
      "clouds_pct": 0,
      "visibility_m": 10000,
      "sunrise": 1783982092,
      "sunset": 1784024072,
      "view_index": 100,
      "view_rating": "Perfect",
      "timezone": "Asia/Makassar",
      "coords": {
        "lat": -8.57797,
        "lng": 115.22275,
        "n_hotels": 22
      },
      "fetched_at": 1784040805
    },
    "best-bangkok-hotels-view": {
      "temp_c": 29.92,
      "feels_like_c": 36.61,
      "condition_id": 804,
      "condition_main": "Clouds",
      "condition_description": "overcast clouds",
      "clouds_pct": 100,
      "visibility_m": 10000,
      "sunrise": 1783983446,
      "sunset": 1784029772,
      "view_index": 72,
      "view_rating": "Good",
      "timezone": "Asia/Bangkok",
      "coords": {
        "lat": 13.72828,
        "lng": 100.52838,
        "n_hotels": 16
      },
      "fetched_at": 1784040807
    },
    "barcelona-hotels-best-views": {
      "temp_c": 30.4,
      "feels_like_c": 34.52,
      "condition_id": 800,
      "condition_main": "Clear",
      "condition_description": "clear sky",
      "clouds_pct": 10,
      "visibility_m": 10000,
      "sunrise": 1784003385,
      "sunset": 1784057048,
      "view_index": 98,
      "view_rating": "Perfect",
      "timezone": "Europe/Madrid",
      "coords": {
        "lat": 41.38904,
        "lng": 2.16947,
        "n_hotels": 28
      },
      "fetched_at": 1784040809
    },
    "beijing-hotels-best-views": {
      "temp_c": 29.08,
      "feels_like_c": 32,
      "condition_id": 804,
      "condition_main": "Clouds",
      "condition_description": "overcast clouds",
      "clouds_pct": 100,
      "visibility_m": 10000,
      "sunrise": 1783976213,
      "sunset": 1784029364,
      "view_index": 72,
      "view_rating": "Good",
      "timezone": "Asia/Shanghai",
      "coords": {
        "lat": 39.92106,
        "lng": 116.44718,
        "n_hotels": 8
      },
      "fetched_at": 1784040810
    },
    "berlin-hotels-best-views": {
      "temp_c": 23.92,
      "feels_like_c": 23.59,
      "condition_id": 804,
      "condition_main": "Clouds",
      "condition_description": "overcast clouds",
      "clouds_pct": 94,
      "visibility_m": 10000,
      "sunrise": 1783998010,
      "sunset": 1784057040,
      "view_index": 73,
      "view_rating": "Good",
      "timezone": "Europe/Berlin",
      "coords": {
        "lat": 52.51184,
        "lng": 13.38541,
        "n_hotels": 14
      },
      "fetched_at": 1784040812
    },
    "bodrum-hotels-best-views": {
      "temp_c": 32.32,
      "feels_like_c": 36.03,
      "condition_id": 800,
      "condition_main": "Clear",
      "condition_description": "clear sky",
      "clouds_pct": 0,
      "visibility_m": 10000,
      "sunrise": 1783998076,
      "sunset": 1784050247,
      "view_index": 100,
      "view_rating": "Perfect",
      "timezone": "Europe/Istanbul",
      "coords": {
        "lat": 37.0905,
        "lng": 27.39868,
        "n_hotels": 6
      },
      "fetched_at": 1784040814
    },
    "boston-hotels-harbor-skyline-views": {
      "temp_c": 29.48,
      "feels_like_c": 31.7,
      "condition_id": 803,
      "condition_main": "Clouds",
      "condition_description": "broken clouds",
      "clouds_pct": 80,
      "visibility_m": 10000,
      "sunrise": 1784020785,
      "sunset": 1784074799,
      "view_index": 75,
      "view_rating": "Excellent",
      "timezone": "America/New_York",
      "coords": {
        "lat": 42.35288,
        "lng": -71.05388,
        "n_hotels": 15
      },
      "fetched_at": 1784040815
    },
    "brighton-seafront-hotels-view": {
      "temp_c": 28.48,
      "feels_like_c": 28.52,
      "condition_id": 800,
      "condition_main": "Clear",
      "condition_description": "clear sky",
      "clouds_pct": 6,
      "visibility_m": 10000,
      "sunrise": 1784001767,
      "sunset": 1784059773,
      "view_index": 99,
      "view_rating": "Perfect",
      "timezone": "Europe/London",
      "coords": {
        "lat": 50.81998,
        "lng": -0.13627,
        "n_hotels": 8
      },
      "fetched_at": 1784040817
    },
    "brisbane-hotels-apartments-best-views": {
      "temp_c": 12.27,
      "feels_like_c": 11.17,
      "condition_id": 800,
      "condition_main": "Clear",
      "condition_description": "clear sky",
      "clouds_pct": 0,
      "visibility_m": 10000,
      "sunrise": 1784061420,
      "sunset": 1784099410,
      "view_index": 100,
      "view_rating": "Perfect",
      "timezone": "Australia/Brisbane",
      "coords": {
        "lat": -27.4656,
        "lng": 153.02901,
        "n_hotels": 16
      },
      "fetched_at": 1784040819
    },
    "budapest-hotels-best-view": {
      "temp_c": 33.23,
      "feels_like_c": 32.14,
      "condition_id": 802,
      "condition_main": "Clouds",
      "condition_description": "scattered clouds",
      "clouds_pct": 25,
      "visibility_m": 10000,
      "sunrise": 1783998034,
      "sunset": 1784054297,
      "view_index": 83,
      "view_rating": "Excellent",
      "timezone": "Europe/Budapest",
      "coords": {
        "lat": 47.49781,
        "lng": 19.04878,
        "n_hotels": 15
      },
      "fetched_at": 1784040820
    },
    "buenos-aires-hotels-best-views": {
      "temp_c": 11.75,
      "feels_like_c": 11.1,
      "condition_id": 803,
      "condition_main": "Clouds",
      "condition_description": "broken clouds",
      "clouds_pct": 70,
      "visibility_m": 10000,
      "sunrise": 1784026696,
      "sunset": 1784062801,
      "view_index": 76,
      "view_rating": "Excellent",
      "timezone": "America/Argentina/Buenos_Aires",
      "coords": {
        "lat": -34.60298,
        "lng": -58.37387,
        "n_hotels": 12
      },
      "fetched_at": 1784040822
    },
    "cairo-hotels-pyramid-nile-view": {
      "temp_c": 38.84,
      "feels_like_c": 37.07,
      "condition_id": 800,
      "condition_main": "Clear",
      "condition_description": "clear sky",
      "clouds_pct": 0,
      "visibility_m": 10000,
      "sunrise": 1783998200,
      "sunset": 1784048295,
      "view_index": 100,
      "view_rating": "Perfect",
      "timezone": "Africa/Cairo",
      "coords": {
        "lat": 30.03364,
        "lng": 31.20666,
        "n_hotels": 10
      },
      "fetched_at": 1784040824
    },
    "cancun-hotels-resorts-best-view": {
      "temp_c": 31.16,
      "feels_like_c": 38.16,
      "condition_id": 800,
      "condition_main": "Clear",
      "condition_description": "clear sky",
      "clouds_pct": 8,
      "visibility_m": 10000,
      "sunrise": 1784027620,
      "sunset": 1784075519,
      "view_index": 99,
      "view_rating": "Perfect",
      "timezone": "America/Cancun",
      "coords": {
        "lat": 21.11642,
        "lng": -86.79281,
        "n_hotels": 10
      },
      "fetched_at": 1784040826
    },
    "best-cannon-beach-hotels-oceanfront-view": {
      "temp_c": 13.1,
      "feels_like_c": 12.84,
      "condition_id": 800,
      "condition_main": "Clear",
      "condition_description": "clear sky",
      "clouds_pct": 1,
      "visibility_m": 10000,
      "sunrise": 1784032755,
      "sunset": 1784088227,
      "view_index": 100,
      "view_rating": "Perfect",
      "timezone": "America/Los_Angeles",
      "coords": {
        "lat": 45.88551,
        "lng": -123.96217,
        "n_hotels": 7
      },
      "fetched_at": 1784040827
    },
    "cape-town-best-hotels-view": {
      "temp_c": 13.5,
      "feels_like_c": 12.86,
      "condition_id": 804,
      "condition_main": "Clouds",
      "condition_description": "overcast clouds",
      "clouds_pct": 98,
      "visibility_m": 10000,
      "sunrise": 1784008180,
      "sunset": 1784044463,
      "view_index": 72,
      "view_rating": "Good",
      "timezone": "Africa/Johannesburg",
      "coords": {
        "lat": -33.93025,
        "lng": 18.39904,
        "n_hotels": 19
      },
      "fetched_at": 1784040829
    },
    "cascais-estoril-hotels-best-views": {
      "temp_c": 23.05,
      "feels_like_c": 23.55,
      "condition_id": 800,
      "condition_main": "Clear",
      "condition_description": "clear sky",
      "clouds_pct": 0,
      "visibility_m": 10000,
      "sunrise": 1784006650,
      "sunset": 1784059349,
      "view_index": 100,
      "view_rating": "Perfect",
      "timezone": "Europe/Lisbon",
      "coords": {
        "lat": 38.70065,
        "lng": -9.42318,
        "n_hotels": 12
      },
      "fetched_at": 1784040831
    },
    "chicago-hotels-romantic-lake-views": {
      "temp_c": 30.32,
      "feels_like_c": 34.35,
      "condition_id": 800,
      "condition_main": "Clear",
      "condition_description": "clear sky",
      "clouds_pct": 4,
      "visibility_m": 10000,
      "sunrise": 1784024853,
      "sunset": 1784078686,
      "view_index": 99,
      "view_rating": "Perfect",
      "timezone": "America/Chicago",
      "coords": {
        "lat": 41.89166,
        "lng": -87.62654,
        "n_hotels": 22
      },
      "fetched_at": 1784040833
    },
    "copenhagen-hotels-best-views": {
      "temp_c": 26.21,
      "feels_like_c": 26.21,
      "condition_id": 804,
      "condition_main": "Clouds",
      "condition_description": "overcast clouds",
      "clouds_pct": 100,
      "visibility_m": 10000,
      "sunrise": 1783997094,
      "sunset": 1784058344,
      "view_index": 72,
      "view_rating": "Good",
      "timezone": "Europe/Copenhagen",
      "coords": {
        "lat": 55.66829,
        "lng": 12.57766,
        "n_hotels": 16
      },
      "fetched_at": 1784040835
    },
    "hotels-cornwall-sea-views": {
      "temp_c": 21.5,
      "feels_like_c": 21.12,
      "condition_id": 803,
      "condition_main": "Clouds",
      "condition_description": "broken clouds",
      "clouds_pct": 57,
      "visibility_m": 10000,
      "sunrise": 1784003093,
      "sunset": 1784060842,
      "view_index": 78,
      "view_rating": "Excellent",
      "timezone": "Europe/London",
      "coords": {
        "lat": 50.37017,
        "lng": -5.12367,
        "n_hotels": 9
      },
      "fetched_at": 1784040836
    },
    "dallas-hotels-best-views": {
      "temp_c": 27.53,
      "feels_like_c": 31.21,
      "condition_id": 801,
      "condition_main": "Clouds",
      "condition_description": "few clouds",
      "clouds_pct": 23,
      "visibility_m": 10000,
      "sunrise": 1784028555,
      "sunset": 1784079396,
      "view_index": 84,
      "view_rating": "Excellent",
      "timezone": "America/Chicago",
      "coords": {
        "lat": 32.79432,
        "lng": -96.81699,
        "n_hotels": 13
      },
      "fetched_at": 1784040838
    },
    "daytona-beach-oceanfront-hotels-view": {
      "temp_c": 29.7,
      "feels_like_c": 35.49,
      "condition_id": 803,
      "condition_main": "Clouds",
      "condition_description": "broken clouds",
      "clouds_pct": 57,
      "visibility_m": 10000,
      "sunrise": 1784025248,
      "sunset": 1784075112,
      "view_index": 78,
      "view_rating": "Excellent",
      "timezone": "America/New_York",
      "coords": {
        "lat": 29.21966,
        "lng": -81.00404,
        "n_hotels": 5
      },
      "fetched_at": 1784040840
    },
    "doha-hotels-resorts-best-views": {
      "temp_c": 35.08,
      "feels_like_c": 41.27,
      "condition_id": 802,
      "condition_main": "Clouds",
      "condition_description": "scattered clouds",
      "clouds_pct": 25,
      "visibility_m": 10000,
      "sunrise": 1783993919,
      "sunset": 1784042821,
      "view_index": 83,
      "view_rating": "Excellent",
      "timezone": "Asia/Qatar",
      "coords": {
        "lat": 25.34579,
        "lng": 51.52785,
        "n_hotels": 15
      },
      "fetched_at": 1784040841
    },
    "dubai-hotels-best-views": {
      "temp_c": 34.39,
      "feels_like_c": 41.39,
      "condition_id": 803,
      "condition_main": "Clouds",
      "condition_description": "broken clouds",
      "clouds_pct": 71,
      "visibility_m": 10000,
      "sunrise": 1783993059,
      "sunset": 1784041916,
      "view_index": 76,
      "view_rating": "Excellent",
      "timezone": "Asia/Dubai",
      "coords": {
        "lat": 25.15493,
        "lng": 55.20457,
        "n_hotels": 21
      },
      "fetched_at": 1784040843
    },
    "edinburgh-hotels-best-views": {
      "temp_c": 17.21,
      "feels_like_c": 16.76,
      "condition_id": 803,
      "condition_main": "Clouds",
      "condition_description": "broken clouds",
      "clouds_pct": 64,
      "visibility_m": 10000,
      "sunrise": 1784000773,
      "sunset": 1784062238,
      "view_index": 77,
      "view_rating": "Excellent",
      "timezone": "Europe/London",
      "coords": {
        "lat": 55.95066,
        "lng": -3.19671,
        "n_hotels": 9
      },
      "fetched_at": 1784040845
    },
    "florence-hotel-views": {
      "temp_c": 38.12,
      "feels_like_c": 39.65,
      "condition_id": 801,
      "condition_main": "Clouds",
      "condition_description": "few clouds",
      "clouds_pct": 24,
      "visibility_m": 10000,
      "sunrise": 1784000736,
      "sunset": 1784055335,
      "view_index": 83,
      "view_rating": "Excellent",
      "timezone": "Europe/Rome",
      "coords": {
        "lat": 43.77433,
        "lng": 11.25936,
        "n_hotels": 15
      },
      "fetched_at": 1784040846
    },
    "fort-lauderdale-hotels-ocean-view": {
      "temp_c": 32.48,
      "feels_like_c": 39.48,
      "condition_id": 803,
      "condition_main": "Clouds",
      "condition_description": "broken clouds",
      "clouds_pct": 51,
      "visibility_m": 10000,
      "sunrise": 1784025425,
      "sunset": 1784074504,
      "view_index": 79,
      "view_rating": "Excellent",
      "timezone": "America/New_York",
      "coords": {
        "lat": 26.12635,
        "lng": -80.10526,
        "n_hotels": 8
      },
      "fetched_at": 1784040848
    },
    "funchal-hotels-ocean-view": {
      "temp_c": 24.66,
      "feels_like_c": 25.56,
      "condition_id": 801,
      "condition_main": "Clouds",
      "condition_description": "few clouds",
      "clouds_pct": 19,
      "visibility_m": 10000,
      "sunrise": 1784009393,
      "sunset": 1784060204,
      "view_index": 84,
      "view_rating": "Excellent",
      "timezone": "Atlantic/Madeira",
      "coords": {
        "lat": 32.64294,
        "lng": -16.92045,
        "n_hotels": 8
      },
      "fetched_at": 1784040850
    },
    "geneva-hotels-best-lake-geneva-views": {
      "temp_c": 33.37,
      "feels_like_c": 31.91,
      "condition_id": 802,
      "condition_main": "Clouds",
      "condition_description": "scattered clouds",
      "clouds_pct": 41,
      "visibility_m": 10000,
      "sunrise": 1784001435,
      "sunset": 1784057089,
      "view_index": 81,
      "view_rating": "Excellent",
      "timezone": "Europe/Zurich",
      "coords": {
        "lat": 46.21124,
        "lng": 6.14663,
        "n_hotels": 8
      },
      "fetched_at": 1784040852
    },
    "gold-coast-hotels-best-view": {
      "temp_c": 13.5,
      "feels_like_c": 12.18,
      "condition_id": 800,
      "condition_main": "Clear",
      "condition_description": "clear sky",
      "clouds_pct": 0,
      "visibility_m": 10000,
      "sunrise": 1784061388,
      "sunset": 1784099245,
      "view_index": 100,
      "view_rating": "Perfect",
      "timezone": "Australia/Brisbane",
      "coords": {
        "lat": -28.01806,
        "lng": 153.43824,
        "n_hotels": 11
      },
      "fetched_at": 1784040853
    },
    "guangzhou-hotels-best-views": {
      "temp_c": 26.72,
      "feels_like_c": 29.21,
      "condition_id": 804,
      "condition_main": "Clouds",
      "condition_description": "overcast clouds",
      "clouds_pct": 100,
      "visibility_m": 10000,
      "sunrise": 1783979348,
      "sunset": 1784027726,
      "view_index": 72,
      "view_rating": "Good",
      "timezone": "Asia/Shanghai",
      "coords": {
        "lat": 23.11672,
        "lng": 113.32882,
        "n_hotels": 9
      },
      "fetched_at": 1784040855
    },
    "half-moon-bay-hotels-best-ocean-view": {
      "temp_c": 17.95,
      "feels_like_c": 17.89,
      "condition_id": 800,
      "condition_main": "Clear",
      "condition_description": "clear sky",
      "clouds_pct": 1,
      "visibility_m": 10000,
      "sunrise": 1784033996,
      "sunset": 1784086267,
      "view_index": 100,
      "view_rating": "Perfect",
      "timezone": "America/Los_Angeles",
      "coords": {
        "lat": 37.4834,
        "lng": -122.46505,
        "n_hotels": 4
      },
      "fetched_at": 1784040857
    },
    "hamburg-hotels-best-views": {
      "temp_c": 25.81,
      "feels_like_c": 25.31,
      "condition_id": 802,
      "condition_main": "Clouds",
      "condition_description": "scattered clouds",
      "clouds_pct": 37,
      "visibility_m": 10000,
      "sunrise": 1783998484,
      "sunset": 1784058194,
      "view_index": 81,
      "view_rating": "Excellent",
      "timezone": "Europe/Berlin",
      "coords": {
        "lat": 53.55457,
        "lng": 9.99033,
        "n_hotels": 12
      },
      "fetched_at": 1784040858
    },
    "hong-kong-hotel-views": {
      "temp_c": 27.52,
      "feels_like_c": 30.33,
      "condition_id": 804,
      "condition_main": "Clouds",
      "condition_description": "overcast clouds",
      "clouds_pct": 100,
      "visibility_m": 6800,
      "sunrise": 1783979241,
      "sunset": 1784027427,
      "view_index": 56,
      "view_rating": "Fair",
      "timezone": "Asia/Hong_Kong",
      "coords": {
        "lat": 22.29116,
        "lng": 114.17218,
        "n_hotels": 15
      },
      "fetched_at": 1784040860
    },
    "honolulu-hotels-best-waikiki-view": {
      "temp_c": 23.03,
      "feels_like_c": 23.53,
      "condition_id": 803,
      "condition_main": "Clouds",
      "condition_description": "broken clouds",
      "clouds_pct": 84,
      "visibility_m": 10000,
      "sunrise": 1784044655,
      "sunset": 1784092584,
      "view_index": 74,
      "view_rating": "Excellent",
      "timezone": "Pacific/Honolulu",
      "coords": {
        "lat": 21.27936,
        "lng": -157.82665,
        "n_hotels": 13
      },
      "fetched_at": 1784040862
    },
    "istanbul-hotels-best-views": {
      "temp_c": 26.42,
      "feels_like_c": 26.42,
      "condition_id": 800,
      "condition_main": "Clear",
      "condition_description": "clear sky",
      "clouds_pct": 0,
      "visibility_m": 10000,
      "sunrise": 1783997010,
      "sunset": 1784050547,
      "view_index": 100,
      "view_rating": "Perfect",
      "timezone": "Europe/Istanbul",
      "coords": {
        "lat": 41.03505,
        "lng": 28.99479,
        "n_hotels": 17
      },
      "fetched_at": 1784040863
    },
    "kuala-lumpur-hotels-best-views": {
      "temp_c": 28.46,
      "feels_like_c": 28.41,
      "condition_id": 804,
      "condition_main": "Clouds",
      "condition_description": "overcast clouds",
      "clouds_pct": 100,
      "visibility_m": 10000,
      "sunrise": 1783984209,
      "sunset": 1784028443,
      "view_index": 72,
      "view_rating": "Good",
      "timezone": "Asia/Kuala_Lumpur",
      "coords": {
        "lat": 3.15492,
        "lng": 101.70751,
        "n_hotels": 9
      },
      "fetched_at": 1784040865
    },
    "laguna-beach-hotels-ocean-view": {
      "temp_c": 20.95,
      "feels_like_c": 21.45,
      "condition_id": 800,
      "condition_main": "Clear",
      "condition_description": "clear sky",
      "clouds_pct": 4,
      "visibility_m": 10000,
      "sunrise": 1784033479,
      "sunset": 1784084529,
      "view_index": 99,
      "view_rating": "Perfect",
      "timezone": "America/Los_Angeles",
      "coords": {
        "lat": 33.5262,
        "lng": -117.76775,
        "n_hotels": 6
      },
      "fetched_at": 1784040867
    },
    "lake-como-hotels-best-views": {
      "temp_c": 32.22,
      "feels_like_c": 33.39,
      "condition_id": 804,
      "condition_main": "Clouds",
      "condition_description": "overcast clouds",
      "clouds_pct": 95,
      "visibility_m": 10000,
      "sunrise": 1784000789,
      "sunset": 1784056299,
      "view_index": 73,
      "view_rating": "Good",
      "timezone": "Europe/Rome",
      "coords": {
        "lat": 45.89099,
        "lng": 9.13852,
        "n_hotels": 10
      },
      "fetched_at": 1784040868
    },
    "lake-district-hotels-best-view": {
      "temp_c": 24.55,
      "feels_like_c": 24.52,
      "condition_id": 804,
      "condition_main": "Clouds",
      "condition_description": "overcast clouds",
      "clouds_pct": 100,
      "visibility_m": 10000,
      "sunrise": 1784001301,
      "sunset": 1784061593,
      "view_index": 72,
      "view_rating": "Good",
      "timezone": "Europe/London",
      "coords": {
        "lat": 54.39498,
        "lng": -2.95563,
        "n_hotels": 9
      },
      "fetched_at": 1784040870
    },
    "lake-garda-hotels-best-views-romantic-holidays": {
      "temp_c": 33.13,
      "feels_like_c": 38.11,
      "condition_id": 803,
      "condition_main": "Clouds",
      "condition_description": "broken clouds",
      "clouds_pct": 58,
      "visibility_m": 10000,
      "sunrise": 1784000471,
      "sunset": 1784055883,
      "view_index": 78,
      "view_rating": "Excellent",
      "timezone": "Europe/Rome",
      "coords": {
        "lat": 45.67091,
        "lng": 10.66754,
        "n_hotels": 8
      },
      "fetched_at": 1784040872
    },
    "las-vegas-hotels-strip-view": {
      "temp_c": 31.97,
      "feels_like_c": 31.73,
      "condition_id": 803,
      "condition_main": "Clouds",
      "condition_description": "broken clouds",
      "clouds_pct": 69,
      "visibility_m": 10000,
      "sunrise": 1784032463,
      "sunset": 1784084298,
      "view_index": 77,
      "view_rating": "Excellent",
      "timezone": "America/Los_Angeles",
      "coords": {
        "lat": 36.11903,
        "lng": -115.1705,
        "n_hotels": 12
      },
      "fetched_at": 1784040874
    },
    "lisbon-hotels-best-views": {
      "temp_c": 25.45,
      "feels_like_c": 25.64,
      "condition_id": 800,
      "condition_main": "Clear",
      "condition_description": "clear sky",
      "clouds_pct": 0,
      "visibility_m": 10000,
      "sunrise": 1784006580,
      "sunset": 1784059286,
      "view_index": 100,
      "view_rating": "Perfect",
      "timezone": "Europe/Lisbon",
      "coords": {
        "lat": 38.71956,
        "lng": -9.1466,
        "n_hotels": 22
      },
      "fetched_at": 1784040875
    },
    "llandudno-seafront-hotels-sea-view": {
      "temp_c": 21.63,
      "feels_like_c": 21.68,
      "condition_id": 803,
      "condition_main": "Clouds",
      "condition_description": "broken clouds",
      "clouds_pct": 61,
      "visibility_m": 10000,
      "sunrise": 1784001879,
      "sunset": 1784061431,
      "view_index": 78,
      "view_rating": "Excellent",
      "timezone": "Europe/London",
      "coords": {
        "lat": 53.32395,
        "lng": -3.82085,
        "n_hotels": 5
      },
      "fetched_at": 1784040877
    },
    "london-hotel-views": {
      "temp_c": 29.01,
      "feels_like_c": 29.44,
      "condition_id": 800,
      "condition_main": "Clear",
      "condition_description": "clear sky",
      "clouds_pct": 1,
      "visibility_m": 10000,
      "sunrise": 1784001557,
      "sunset": 1784059965,
      "view_index": 100,
      "view_rating": "Perfect",
      "timezone": "Europe/London",
      "coords": {
        "lat": 51.50727,
        "lng": -0.09623,
        "n_hotels": 25
      },
      "fetched_at": 1784040879
    },
    "hotels-los-angeles-best-views": {
      "temp_c": 22.22,
      "feels_like_c": 22.43,
      "condition_id": 800,
      "condition_main": "Clear",
      "condition_description": "clear sky",
      "clouds_pct": 0,
      "visibility_m": 10000,
      "sunrise": 1784033536,
      "sunset": 1784084747,
      "view_index": 100,
      "view_rating": "Perfect",
      "timezone": "America/Los_Angeles",
      "coords": {
        "lat": 34.07482,
        "lng": -118.34114,
        "n_hotels": 14
      },
      "fetched_at": 1784040880
    },
    "lugano-hotels-best-lake-views": {
      "temp_c": 31.32,
      "feels_like_c": 31.04,
      "condition_id": 804,
      "condition_main": "Clouds",
      "condition_description": "overcast clouds",
      "clouds_pct": 90,
      "visibility_m": 10000,
      "sunrise": 1784000810,
      "sunset": 1784056365,
      "view_index": 74,
      "view_rating": "Excellent",
      "timezone": "Europe/Zurich",
      "coords": {
        "lat": 45.98958,
        "lng": 8.95834,
        "n_hotels": 9
      },
      "fetched_at": 1784040882
    },
    "lyon-hotels-best-views": {
      "temp_c": 36.16,
      "feels_like_c": 36.67,
      "condition_id": 803,
      "condition_main": "Clouds",
      "condition_description": "broken clouds",
      "clouds_pct": 81,
      "visibility_m": 10000,
      "sunrise": 1784001852,
      "sunset": 1784057302,
      "view_index": 75,
      "view_rating": "Excellent",
      "timezone": "Europe/Paris",
      "coords": {
        "lat": 45.75924,
        "lng": 4.83478,
        "n_hotels": 5
      },
      "fetched_at": 1784040884
    },
    "madeira-best-hotels-ocean-view": {
      "temp_c": 13.85,
      "feels_like_c": 13.59,
      "condition_id": 801,
      "condition_main": "Clouds",
      "condition_description": "few clouds",
      "clouds_pct": 17,
      "visibility_m": 10000,
      "sunrise": 1784009412,
      "sunset": 1784060251,
      "view_index": 84,
      "view_rating": "Excellent",
      "timezone": "Atlantic/Madeira",
      "coords": {
        "lat": 32.74172,
        "lng": -17.05553,
        "n_hotels": 6
      },
      "fetched_at": 1784040886
    },
    "madrid-hotels-best-views": {
      "temp_c": 34.66,
      "feels_like_c": 32.39,
      "condition_id": 802,
      "condition_main": "Clouds",
      "condition_description": "scattered clouds",
      "clouds_pct": 44,
      "visibility_m": 10000,
      "sunrise": 1784004975,
      "sunset": 1784058279,
      "view_index": 80,
      "view_rating": "Excellent",
      "timezone": "Europe/Madrid",
      "coords": {
        "lat": 40.42373,
        "lng": -3.70112,
        "n_hotels": 20
      },
      "fetched_at": 1784040887
    },
    "maldives-hotels-ocean-view": {
      "temp_c": 27.98,
      "feels_like_c": 31.03,
      "condition_id": 804,
      "condition_main": "Clouds",
      "condition_description": "overcast clouds",
      "clouds_pct": 100,
      "visibility_m": 10000,
      "sunrise": 1783990930,
      "sunset": 1784035366,
      "view_index": 72,
      "view_rating": "Good",
      "timezone": "Indian/Maldives",
      "coords": {
        "lat": 4.2017,
        "lng": 73.2855,
        "n_hotels": 11
      },
      "fetched_at": 1784040889
    },
    "mallorca-hotels-best-sea-views": {
      "temp_c": 32.81,
      "feels_like_c": 38.36,
      "condition_id": 802,
      "condition_main": "Clouds",
      "condition_description": "scattered clouds",
      "clouds_pct": 34,
      "visibility_m": 10000,
      "sunrise": 1784003555,
      "sunset": 1784056598,
      "view_index": 82,
      "view_rating": "Excellent",
      "timezone": "Europe/Madrid",
      "coords": {
        "lat": 39.68307,
        "lng": 2.75656,
        "n_hotels": 8
      },
      "fetched_at": 1784040891
    },
    "manila-hotels-best-view": {
      "temp_c": 28.42,
      "feels_like_c": 33.92,
      "condition_id": 804,
      "condition_main": "Clouds",
      "condition_description": "overcast clouds",
      "clouds_pct": 100,
      "visibility_m": 10000,
      "sunrise": 1783978442,
      "sunset": 1784024939,
      "view_index": 72,
      "view_rating": "Good",
      "timezone": "Asia/Manila",
      "coords": {
        "lat": 14.54963,
        "lng": 121.02071,
        "n_hotels": 7
      },
      "fetched_at": 1784040892
    },
    "marrakech-hotels-medina-atlas-view": {
      "temp_c": 37.01,
      "feels_like_c": 35.59,
      "condition_id": 800,
      "condition_main": "Clear",
      "condition_description": "clear sky",
      "clouds_pct": 10,
      "visibility_m": 10000,
      "sunrise": 1784007398,
      "sunset": 1784057918,
      "view_index": 98,
      "view_rating": "Perfect",
      "timezone": "Africa/Casablanca",
      "coords": {
        "lat": 31.60751,
        "lng": -8.00043,
        "n_hotels": 9
      },
      "fetched_at": 1784040894
    },
    "hotels-marseille-best-view": {
      "temp_c": 29.99,
      "feels_like_c": 32.62,
      "condition_id": 800,
      "condition_main": "Clear",
      "condition_description": "clear sky",
      "clouds_pct": 2,
      "visibility_m": 10000,
      "sunrise": 1784002249,
      "sunset": 1784056651,
      "view_index": 100,
      "view_rating": "Perfect",
      "timezone": "Europe/Paris",
      "coords": {
        "lat": 43.28922,
        "lng": 5.36508,
        "n_hotels": 8
      },
      "fetched_at": 1784040896
    },
    "melbourne-hotels-best-views": {
      "temp_c": 7.9,
      "feels_like_c": 6.21,
      "condition_id": 800,
      "condition_main": "Clear",
      "condition_description": "clear sky",
      "clouds_pct": 3,
      "visibility_m": 10000,
      "sunrise": 1784064761,
      "sunset": 1784099939,
      "view_index": 100,
      "view_rating": "Perfect",
      "timezone": "Australia/Melbourne",
      "coords": {
        "lat": -37.82048,
        "lng": 144.96475,
        "n_hotels": 19
      },
      "fetched_at": 1784040897
    },
    "mexico-city-hotels-best-views": {
      "temp_c": 13.82,
      "feels_like_c": 13.24,
      "condition_id": 803,
      "condition_main": "Clouds",
      "condition_description": "broken clouds",
      "clouds_pct": 59,
      "visibility_m": 10000,
      "sunrise": 1784030779,
      "sunset": 1784078302,
      "view_index": 78,
      "view_rating": "Excellent",
      "timezone": "America/Mexico_City",
      "coords": {
        "lat": 19.43095,
        "lng": -99.17205,
        "n_hotels": 11
      },
      "fetched_at": 1784040899
    },
    "miami-beach-best-oceanfront-hotels-view": {
      "temp_c": 31.96,
      "feels_like_c": 38.96,
      "condition_id": 500,
      "condition_main": "Rain",
      "condition_description": "light rain",
      "clouds_pct": 83,
      "visibility_m": 10000,
      "sunrise": 1784025469,
      "sunset": 1784074470,
      "view_index": 63,
      "view_rating": "Good",
      "timezone": "America/New_York",
      "coords": {
        "lat": 25.81174,
        "lng": -80.12671,
        "n_hotels": 18
      },
      "fetched_at": 1784040901
    },
    "mumbai-hotels-best-sea-view": {
      "temp_c": 28.93,
      "feels_like_c": 33.33,
      "condition_id": 804,
      "condition_main": "Clouds",
      "condition_description": "overcast clouds",
      "clouds_pct": 100,
      "visibility_m": 10000,
      "sunrise": 1783989539,
      "sunset": 1784036977,
      "view_index": 72,
      "view_rating": "Good",
      "timezone": "Asia/Kolkata",
      "coords": {
        "lat": 18.97652,
        "lng": 72.82602,
        "n_hotels": 10
      },
      "fetched_at": 1784040903
    },
    "munich-hotels-best-views": {
      "temp_c": 29.08,
      "feels_like_c": 29.76,
      "condition_id": 804,
      "condition_main": "Clouds",
      "condition_description": "overcast clouds",
      "clouds_pct": 93,
      "visibility_m": 10000,
      "sunrise": 1783999673,
      "sunset": 1784056248,
      "view_index": 73,
      "view_rating": "Good",
      "timezone": "Europe/Berlin",
      "coords": {
        "lat": 48.13941,
        "lng": 11.57161,
        "n_hotels": 7
      },
      "fetched_at": 1784040904
    },
    "mykonos-hotels-best-views": {
      "temp_c": 27.83,
      "feels_like_c": 29.1,
      "condition_id": 800,
      "condition_main": "Clear",
      "condition_description": "clear sky",
      "clouds_pct": 0,
      "visibility_m": 10000,
      "sunrise": 1783998511,
      "sunset": 1784050793,
      "view_index": 100,
      "view_rating": "Perfect",
      "timezone": "Europe/Athens",
      "coords": {
        "lat": 37.43055,
        "lng": 25.35468,
        "n_hotels": 17
      },
      "fetched_at": 1784040906
    },
    "myrtle-beach-hotels-ocean-view": {
      "temp_c": 28.79,
      "feels_like_c": 34.16,
      "condition_id": 804,
      "condition_main": "Clouds",
      "condition_description": "overcast clouds",
      "clouds_pct": 100,
      "visibility_m": 10000,
      "sunrise": 1784024114,
      "sunset": 1784075221,
      "view_index": 72,
      "view_rating": "Good",
      "timezone": "America/New_York",
      "coords": {
        "lat": 33.70003,
        "lng": -78.86787,
        "n_hotels": 14
      },
      "fetched_at": 1784040908
    },
    "napa-valley-hotels-vineyard-view": {
      "temp_c": 22.55,
      "feels_like_c": 22.27,
      "condition_id": 800,
      "condition_main": "Clear",
      "condition_description": "clear sky",
      "clouds_pct": 9,
      "visibility_m": 10000,
      "sunrise": 1784033828,
      "sunset": 1784086417,
      "view_index": 99,
      "view_rating": "Perfect",
      "timezone": "America/Los_Angeles",
      "coords": {
        "lat": 38.44304,
        "lng": -122.42783,
        "n_hotels": 7
      },
      "fetched_at": 1784040909
    },
    "new-york-hotel-views": {
      "temp_c": 29.3,
      "feels_like_c": 30.61,
      "condition_id": 802,
      "condition_main": "Clouds",
      "condition_description": "scattered clouds",
      "clouds_pct": 26,
      "visibility_m": 10000,
      "sunrise": 1784021793,
      "sunset": 1784075198,
      "view_index": 83,
      "view_rating": "Excellent",
      "timezone": "America/New_York",
      "coords": {
        "lat": 40.73836,
        "lng": -73.98649,
        "n_hotels": 32
      },
      "fetched_at": 1784040911
    },
    "niagara-falls-hotels-with-falls-view-canada": {
      "temp_c": 28.38,
      "feels_like_c": 32.05,
      "condition_id": 802,
      "condition_main": "Clouds",
      "condition_description": "scattered clouds",
      "clouds_pct": 42,
      "visibility_m": 10000,
      "sunrise": 1784022569,
      "sunset": 1784076868,
      "view_index": 81,
      "view_rating": "Excellent",
      "timezone": "America/Toronto",
      "coords": {
        "lat": 43.08207,
        "lng": -79.08055,
        "n_hotels": 10
      },
      "fetched_at": 1784040913
    },
    "nice-hotels-best-beach-views": {
      "temp_c": 32.48,
      "feels_like_c": 39.48,
      "condition_id": 800,
      "condition_main": "Clear",
      "condition_description": "clear sky",
      "clouds_pct": 5,
      "visibility_m": 10000,
      "sunrise": 1784001708,
      "sunset": 1784056279,
      "view_index": 99,
      "view_rating": "Perfect",
      "timezone": "Europe/Paris",
      "coords": {
        "lat": 43.69547,
        "lng": 7.26513,
        "n_hotels": 6
      },
      "fetched_at": 1784040915
    },
    "osaka-hotels-best-views": {
      "temp_c": 31.06,
      "feels_like_c": 36.58,
      "condition_id": 804,
      "condition_main": "Clouds",
      "condition_description": "overcast clouds",
      "clouds_pct": 100,
      "visibility_m": 10000,
      "sunrise": 1783972495,
      "sunset": 1784023934,
      "view_index": 72,
      "view_rating": "Good",
      "timezone": "Asia/Tokyo",
      "coords": {
        "lat": 34.68533,
        "lng": 135.49839,
        "n_hotels": 14
      },
      "fetched_at": 1784040916
    },
    "paris-hotels-eiffel-tower-view": {
      "temp_c": 35.17,
      "feels_like_c": 35.61,
      "condition_id": 804,
      "condition_main": "Clouds",
      "condition_description": "overcast clouds",
      "clouds_pct": 97,
      "visibility_m": 10000,
      "sunrise": 1784001713,
      "sunset": 1784058654,
      "view_index": 72,
      "view_rating": "Good",
      "timezone": "Europe/Paris",
      "coords": {
        "lat": 48.86487,
        "lng": 2.30872,
        "n_hotels": 28
      },
      "fetched_at": 1784040918
    },
    "paros-hotels-best-sea-views": {
      "temp_c": 28.56,
      "feels_like_c": 29.44,
      "condition_id": 800,
      "condition_main": "Clear",
      "condition_description": "clear sky",
      "clouds_pct": 0,
      "visibility_m": 10000,
      "sunrise": 1783998604,
      "sunset": 1784050771,
      "view_index": 100,
      "view_rating": "Perfect",
      "timezone": "Europe/Athens",
      "coords": {
        "lat": 37.07985,
        "lng": 25.20619,
        "n_hotels": 10
      },
      "fetched_at": 1784040920
    },
    "perth-hotels-best-views": {
      "temp_c": 13.73,
      "feels_like_c": 12.83,
      "condition_id": 800,
      "condition_main": "Clear",
      "condition_description": "clear sky",
      "clouds_pct": 0,
      "visibility_m": 10000,
      "sunrise": 1783984523,
      "sunset": 1784021331,
      "view_index": 100,
      "view_rating": "Perfect",
      "timezone": "Australia/Perth",
      "coords": {
        "lat": -31.95531,
        "lng": 115.86824,
        "n_hotels": 10
      },
      "fetched_at": 1784040921
    },
    "phuket-hotels-best-beachfront-views": {
      "temp_c": 28.7,
      "feels_like_c": 35.7,
      "condition_id": 804,
      "condition_main": "Clouds",
      "condition_description": "overcast clouds",
      "clouds_pct": 100,
      "visibility_m": 10000,
      "sunrise": 1783984552,
      "sunset": 1784029720,
      "view_index": 72,
      "view_rating": "Good",
      "timezone": "Asia/Bangkok",
      "coords": {
        "lat": 7.96151,
        "lng": 98.3337,
        "n_hotels": 16
      },
      "fetched_at": 1784040923
    },
    "pismo-beach-hotels-best-oceanfront-views": {
      "temp_c": 20.38,
      "feels_like_c": 20.3,
      "condition_id": 800,
      "condition_main": "Clear",
      "condition_description": "clear sky",
      "clouds_pct": 6,
      "visibility_m": 10000,
      "sunrise": 1784033931,
      "sunset": 1784085463,
      "view_index": 99,
      "view_rating": "Perfect",
      "timezone": "America/Los_Angeles",
      "coords": {
        "lat": 35.1471,
        "lng": -120.65502,
        "n_hotels": 10
      },
      "fetched_at": 1784040925
    },
    "playa-del-carmen-hotels-resorts-best-beachfront-views": {
      "temp_c": 30.49,
      "feels_like_c": 35.22,
      "condition_id": 800,
      "condition_main": "Clear",
      "condition_description": "clear sky",
      "clouds_pct": 8,
      "visibility_m": 10000,
      "sunrise": 1784027733,
      "sunset": 1784075535,
      "view_index": 99,
      "view_rating": "Perfect",
      "timezone": "America/Cancun",
      "coords": {
        "lat": 20.68467,
        "lng": -87.06098,
        "n_hotels": 11
      },
      "fetched_at": 1784040927
    },
    "porto-hotels-best-views": {
      "temp_c": 22.45,
      "feels_like_c": 22.47,
      "condition_id": 801,
      "condition_main": "Clouds",
      "condition_description": "few clouds",
      "clouds_pct": 20,
      "visibility_m": 10000,
      "sunrise": 1784006021,
      "sunset": 1784059591,
      "view_index": 84,
      "view_rating": "Excellent",
      "timezone": "Europe/Lisbon",
      "coords": {
        "lat": 41.1447,
        "lng": -8.6168,
        "n_hotels": 17
      },
      "fetched_at": 1784040928
    },
    "prague-hotels-best-old-town-river-castle-views": {
      "temp_c": 26.71,
      "feels_like_c": 26.99,
      "condition_id": 804,
      "condition_main": "Clouds",
      "condition_description": "overcast clouds",
      "clouds_pct": 85,
      "visibility_m": 9047,
      "sunrise": 1783998480,
      "sunset": 1784056077,
      "view_index": 69,
      "view_rating": "Good",
      "timezone": "Europe/Prague",
      "coords": {
        "lat": 50.08492,
        "lng": 14.4141,
        "n_hotels": 18
      },
      "fetched_at": 1784040930
    },
    "rio-de-janeiro-luxury-hotels-best-beachfront-views": {
      "temp_c": 22.39,
      "feels_like_c": 22.98,
      "condition_id": 802,
      "condition_main": "Clouds",
      "condition_description": "scattered clouds",
      "clouds_pct": 33,
      "visibility_m": 10000,
      "sunrise": 1784021604,
      "sunset": 1784060621,
      "view_index": 82,
      "view_rating": "Excellent",
      "timezone": "America/Sao_Paulo",
      "coords": {
        "lat": -22.96822,
        "lng": -43.22042,
        "n_hotels": 16
      },
      "fetched_at": 1784040932
    },
    "rome-luxury-hotels-best-city-views": {
      "temp_c": 34.32,
      "feels_like_c": 34.1,
      "condition_id": 800,
      "condition_main": "Clear",
      "condition_description": "clear sky",
      "clouds_pct": 6,
      "visibility_m": 10000,
      "sunrise": 1784000813,
      "sunset": 1784054670,
      "view_index": 99,
      "view_rating": "Perfect",
      "timezone": "Europe/Rome",
      "coords": {
        "lat": 41.9039,
        "lng": 12.48076,
        "n_hotels": 19
      },
      "fetched_at": 1784040933
    },
    "saint-tropez-luxury-hotels-best-centre-ville-sea-views": {
      "temp_c": 30.19,
      "feels_like_c": 35.25,
      "condition_id": 800,
      "condition_main": "Clear",
      "condition_description": "clear sky",
      "clouds_pct": 8,
      "visibility_m": 10000,
      "sunrise": 1784001949,
      "sunset": 1784056340,
      "view_index": 99,
      "view_rating": "Perfect",
      "timezone": "Europe/Paris",
      "coords": {
        "lat": 43.26089,
        "lng": 6.63848,
        "n_hotels": 9
      },
      "fetched_at": 1784040935
    },
    "salzburg-hotels-best-old-town-city-center-views": {
      "temp_c": 26.43,
      "feels_like_c": 26.43,
      "condition_id": 802,
      "condition_main": "Clouds",
      "condition_description": "scattered clouds",
      "clouds_pct": 44,
      "visibility_m": 10000,
      "sunrise": 1783999403,
      "sunset": 1784055813,
      "view_index": 80,
      "view_rating": "Excellent",
      "timezone": "Europe/Vienna",
      "coords": {
        "lat": 47.80585,
        "lng": 13.03968,
        "n_hotels": 9
      },
      "fetched_at": 1784040937
    },
    "san-diego-hotels-best-beachfront-views": {
      "temp_c": 22.17,
      "feels_like_c": 22.66,
      "condition_id": 800,
      "condition_main": "Clear",
      "condition_description": "clear sky",
      "clouds_pct": 7,
      "visibility_m": 10000,
      "sunrise": 1784033458,
      "sunset": 1784084288,
      "view_index": 99,
      "view_rating": "Perfect",
      "timezone": "America/Los_Angeles",
      "coords": {
        "lat": 32.76571,
        "lng": -117.22109,
        "n_hotels": 11
      },
      "fetched_at": 1784040938
    },
    "san-francisco-hotels-best-golden-gate-views": {
      "temp_c": 18.28,
      "feels_like_c": 18.04,
      "condition_id": 800,
      "condition_main": "Clear",
      "condition_description": "clear sky",
      "clouds_pct": 9,
      "visibility_m": 10000,
      "sunrise": 1784033932,
      "sunset": 1784086305,
      "view_index": 99,
      "view_rating": "Perfect",
      "timezone": "America/Los_Angeles",
      "coords": {
        "lat": 37.79434,
        "lng": -122.41203,
        "n_hotels": 12
      },
      "fetched_at": 1784040940
    },
    "best-ocean-view-hotels-santa-monica": {
      "temp_c": 21.39,
      "feels_like_c": 21.75,
      "condition_id": 800,
      "condition_main": "Clear",
      "condition_description": "clear sky",
      "clouds_pct": 0,
      "visibility_m": 10000,
      "sunrise": 1784033582,
      "sunset": 1784084773,
      "view_index": 100,
      "view_rating": "Perfect",
      "timezone": "America/Los_Angeles",
      "coords": {
        "lat": 34.00781,
        "lng": -118.49198,
        "n_hotels": 10
      },
      "fetched_at": 1784040942
    },
    "santorini-hotels-best-oia-imerovigli-caldera-views": {
      "temp_c": 25.98,
      "feels_like_c": 25.98,
      "condition_id": 800,
      "condition_main": "Clear",
      "condition_description": "clear sky",
      "clouds_pct": 0,
      "visibility_m": 10000,
      "sunrise": 1783998660,
      "sunset": 1784050622,
      "view_index": 100,
      "view_rating": "Perfect",
      "timezone": "Europe/Athens",
      "coords": {
        "lat": 36.44135,
        "lng": 25.39915,
        "n_hotels": 15
      },
      "fetched_at": 1784040944
    },
    "seattle-hotels-best-space-needle-waterfront-views": {
      "temp_c": 15.57,
      "feels_like_c": 15.14,
      "condition_id": 800,
      "condition_main": "Clear",
      "condition_description": "clear sky",
      "clouds_pct": 0,
      "visibility_m": 10000,
      "sunrise": 1784031963,
      "sunset": 1784088239,
      "view_index": 100,
      "view_rating": "Perfect",
      "timezone": "America/Los_Angeles",
      "coords": {
        "lat": 47.60927,
        "lng": -122.33771,
        "n_hotels": 13
      },
      "fetched_at": 1784040945
    },
    "sedona-hotels-best-red-rock-views": {
      "temp_c": 26,
      "feels_like_c": 26,
      "condition_id": 804,
      "condition_main": "Clouds",
      "condition_description": "overcast clouds",
      "clouds_pct": 100,
      "visibility_m": 10000,
      "sunrise": 1784031843,
      "sunset": 1784083290,
      "view_index": 72,
      "view_rating": "Good",
      "timezone": "America/Phoenix",
      "coords": {
        "lat": 34.86054,
        "lng": -111.77888,
        "n_hotels": 9
      },
      "fetched_at": 1784040947
    },
    "seoul-hotels-best-views": {
      "temp_c": 25.06,
      "feels_like_c": 26.05,
      "condition_id": 503,
      "condition_main": "Rain",
      "condition_description": "very heavy rain",
      "clouds_pct": 100,
      "visibility_m": 10000,
      "sunrise": 1783974088,
      "sunset": 1784026425,
      "view_index": 60,
      "view_rating": "Good",
      "timezone": "Asia/Seoul",
      "coords": {
        "lat": 37.54173,
        "lng": 126.99409,
        "n_hotels": 17
      },
      "fetched_at": 1784040949
    },
    "seville-hotels-best-views": {
      "temp_c": 31.56,
      "feels_like_c": 31.35,
      "condition_id": 802,
      "condition_main": "Clouds",
      "condition_description": "scattered clouds",
      "clouds_pct": 47,
      "visibility_m": 10000,
      "sunrise": 1784006045,
      "sunset": 1784058307,
      "view_index": 80,
      "view_rating": "Excellent",
      "timezone": "Europe/Madrid",
      "coords": {
        "lat": 37.38739,
        "lng": -5.99237,
        "n_hotels": 13
      },
      "fetched_at": 1784040950
    },
    "shanghai-hotels-best-views": {
      "temp_c": 29.56,
      "feels_like_c": 36.56,
      "condition_id": 804,
      "condition_main": "Clouds",
      "condition_description": "overcast clouds",
      "clouds_pct": 100,
      "visibility_m": 10000,
      "sunrise": 1783976358,
      "sunset": 1784026794,
      "view_index": 72,
      "view_rating": "Good",
      "timezone": "Asia/Shanghai",
      "coords": {
        "lat": 31.23627,
        "lng": 121.4966,
        "n_hotels": 11
      },
      "fetched_at": 1784040952
    },
    "sharm-el-sheikh-hotels-red-sea-view": {
      "temp_c": 32.63,
      "feels_like_c": 33.01,
      "condition_id": 800,
      "condition_main": "Clear",
      "condition_description": "clear sky",
      "clouds_pct": 0,
      "visibility_m": 10000,
      "sunrise": 1783997713,
      "sunset": 1784047261,
      "view_index": 100,
      "view_rating": "Perfect",
      "timezone": "Africa/Cairo",
      "coords": {
        "lat": 27.94199,
        "lng": 34.37353,
        "n_hotels": 7
      },
      "fetched_at": 1784040954
    },
    "shenzhen-hotels-best-views": {
      "temp_c": 27.63,
      "feels_like_c": 32.16,
      "condition_id": 804,
      "condition_main": "Clouds",
      "condition_description": "overcast clouds",
      "clouds_pct": 100,
      "visibility_m": 10000,
      "sunrise": 1783979241,
      "sunset": 1784027484,
      "view_index": 72,
      "view_rating": "Good",
      "timezone": "Asia/Shanghai",
      "coords": {
        "lat": 22.53782,
        "lng": 114.05408,
        "n_hotels": 6
      },
      "fetched_at": 1784040956
    },
    "sicily-hotels-best-etna-sea-views": {
      "temp_c": 26.05,
      "feels_like_c": 26.05,
      "condition_id": 800,
      "condition_main": "Clear",
      "condition_description": "clear sky",
      "clouds_pct": 0,
      "visibility_m": 10000,
      "sunrise": 1784000966,
      "sunset": 1784053397,
      "view_index": 100,
      "view_rating": "Perfect",
      "timezone": "Europe/Rome",
      "coords": {
        "lat": 37.88693,
        "lng": 14.81673,
        "n_hotels": 14
      },
      "fetched_at": 1784040957
    },
    "singapore-hotels-best-views": {
      "temp_c": 29.41,
      "feels_like_c": 36.41,
      "condition_id": 803,
      "condition_main": "Clouds",
      "condition_description": "broken clouds",
      "clouds_pct": 62,
      "visibility_m": 10000,
      "sunrise": 1783983873,
      "sunset": 1784027749,
      "view_index": 78,
      "view_rating": "Excellent",
      "timezone": "Asia/Singapore",
      "coords": {
        "lat": 1.29134,
        "lng": 103.85327,
        "n_hotels": 15
      },
      "fetched_at": 1784040959
    },
    "sintra-hotels-best-views": {
      "temp_c": 23.06,
      "feels_like_c": 23.41,
      "condition_id": 800,
      "condition_main": "Clear",
      "condition_description": "clear sky",
      "clouds_pct": 0,
      "visibility_m": 10000,
      "sunrise": 1784006628,
      "sunset": 1784059362,
      "view_index": 100,
      "view_rating": "Perfect",
      "timezone": "Europe/Lisbon",
      "coords": {
        "lat": 38.79918,
        "lng": -9.40526,
        "n_hotels": 8
      },
      "fetched_at": 1784040961
    },
    "stockholm-hotels-best-waterfront-views": {
      "temp_c": 27.38,
      "feels_like_c": 26.94,
      "condition_id": 800,
      "condition_main": "Clear",
      "condition_description": "clear sky",
      "clouds_pct": 0,
      "visibility_m": 10000,
      "sunrise": 1783994108,
      "sunset": 1784058691,
      "view_index": 100,
      "view_rating": "Perfect",
      "timezone": "Europe/Stockholm",
      "coords": {
        "lat": 59.32925,
        "lng": 18.07544,
        "n_hotels": 10
      },
      "fetched_at": 1784040962
    },
    "sydney-hotels-best-harbour-views": {
      "temp_c": 11.86,
      "feels_like_c": 10.8,
      "condition_id": 800,
      "condition_main": "Clear",
      "condition_description": "clear sky",
      "clouds_pct": 0,
      "visibility_m": 10000,
      "sunrise": 1784062682,
      "sunset": 1784099020,
      "view_index": 100,
      "view_rating": "Perfect",
      "timezone": "Australia/Sydney",
      "coords": {
        "lat": -33.86399,
        "lng": 151.21412,
        "n_hotels": 22
      },
      "fetched_at": 1784040964
    },
    "sao-paulo-hotels-best-views": {
      "temp_c": 13.8,
      "feels_like_c": 13.35,
      "condition_id": 803,
      "condition_main": "Clouds",
      "condition_description": "broken clouds",
      "clouds_pct": 78,
      "visibility_m": 10000,
      "sunrise": 1784022502,
      "sunset": 1784061381,
      "view_index": 75,
      "view_rating": "Excellent",
      "timezone": "America/Sao_Paulo",
      "coords": {
        "lat": -23.5932,
        "lng": -46.684,
        "n_hotels": 10
      },
      "fetched_at": 1784040966
    },
    "tokyo-hotels-best-skyline-views": {
      "temp_c": 28.15,
      "feels_like_c": 32.98,
      "condition_id": 804,
      "condition_main": "Clouds",
      "condition_description": "overcast clouds",
      "clouds_pct": 100,
      "visibility_m": 10000,
      "sunrise": 1783971325,
      "sunset": 1784023065,
      "view_index": 72,
      "view_rating": "Good",
      "timezone": "Asia/Tokyo",
      "coords": {
        "lat": 35.67158,
        "lng": 139.74904,
        "n_hotels": 24
      },
      "fetched_at": 1784040967
    },
    "toronto-hotels-best-skyline-views": {
      "temp_c": 31.95,
      "feels_like_c": 37.26,
      "condition_id": 803,
      "condition_main": "Clouds",
      "condition_description": "broken clouds",
      "clouds_pct": 84,
      "visibility_m": 10000,
      "sunrise": 1784022528,
      "sunset": 1784077055,
      "view_index": 74,
      "view_rating": "Excellent",
      "timezone": "America/Toronto",
      "coords": {
        "lat": 43.64986,
        "lng": -79.39163,
        "n_hotels": 10
      },
      "fetched_at": 1784040969
    },
    "vancouver-hotels-best-city-waterfront-views": {
      "temp_c": 18.41,
      "feels_like_c": 17.98,
      "condition_id": 804,
      "condition_main": "Clouds",
      "condition_description": "overcast clouds",
      "clouds_pct": 99,
      "visibility_m": 10000,
      "sunrise": 1784031728,
      "sunset": 1784088850,
      "view_index": 72,
      "view_rating": "Good",
      "timezone": "America/Vancouver",
      "coords": {
        "lat": 49.28496,
        "lng": -123.12034,
        "n_hotels": 14
      },
      "fetched_at": 1784040971
    },
    "venice-hotels-best-canal-views": {
      "temp_c": 32.05,
      "feels_like_c": 34.22,
      "condition_id": 804,
      "condition_main": "Clouds",
      "condition_description": "overcast clouds",
      "clouds_pct": 90,
      "visibility_m": 10000,
      "sunrise": 1784000123,
      "sunset": 1784055430,
      "view_index": 74,
      "view_rating": "Excellent",
      "timezone": "Europe/Rome",
      "coords": {
        "lat": 45.43284,
        "lng": 12.3371,
        "n_hotels": 15
      },
      "fetched_at": 1784040973
    },
    "vienna-hotels-best-city-centre-cathedral-views": {
      "temp_c": 31.51,
      "feels_like_c": 31.43,
      "condition_id": 803,
      "condition_main": "Clouds",
      "condition_description": "broken clouds",
      "clouds_pct": 76,
      "visibility_m": 10000,
      "sunrise": 1783998502,
      "sunset": 1784055113,
      "view_index": 76,
      "view_rating": "Excellent",
      "timezone": "Europe/Vienna",
      "coords": {
        "lat": 48.20805,
        "lng": 16.37553,
        "n_hotels": 15
      },
      "fetched_at": 1784040974
    },
    "virginia-beach-hotels-oceanfront-views": {
      "temp_c": 27.77,
      "feels_like_c": 29.32,
      "condition_id": 800,
      "condition_main": "Clear",
      "condition_description": "clear sky",
      "clouds_pct": 3,
      "visibility_m": 10000,
      "sunrise": 1784022937,
      "sunset": 1784075014,
      "view_index": 100,
      "view_rating": "Perfect",
      "timezone": "America/New_York",
      "coords": {
        "lat": 36.85926,
        "lng": -75.98342,
        "n_hotels": 14
      },
      "fetched_at": 1784040976
    },
    "washington-dc-hotels-best-national-mall-views": {
      "temp_c": 29.26,
      "feels_like_c": 32.53,
      "condition_id": 800,
      "condition_main": "Clear",
      "condition_description": "clear sky",
      "clouds_pct": 0,
      "visibility_m": 10000,
      "sunrise": 1784022852,
      "sunset": 1784075602,
      "view_index": 100,
      "view_rating": "Perfect",
      "timezone": "America/New_York",
      "coords": {
        "lat": 38.88772,
        "lng": -77.03165,
        "n_hotels": 12
      },
      "fetched_at": 1784040978
    },
    "zurich-hotels-best-old-town-lake-views": {
      "temp_c": 32.33,
      "feels_like_c": 32.76,
      "condition_id": 803,
      "condition_main": "Clouds",
      "condition_description": "broken clouds",
      "clouds_pct": 63,
      "visibility_m": 10000,
      "sunrise": 1784000590,
      "sunset": 1784056786,
      "view_index": 78,
      "view_rating": "Excellent",
      "timezone": "Europe/Zurich",
      "coords": {
        "lat": 47.36638,
        "lng": 8.54122,
        "n_hotels": 11
      },
      "fetched_at": 1784040979
    }
  }
}
